odoo/addons/purchase_minimum_amount/README.rst
odoo/addons/purchase_minimum_amount/__init__.py
odoo/addons/purchase_minimum_amount/__manifest__.py
odoo/addons/purchase_minimum_amount/data/purchase_block_reason_data.xml
odoo/addons/purchase_minimum_amount/models/__init__.py
odoo/addons/purchase_minimum_amount/models/partner.py
odoo/addons/purchase_minimum_amount/models/purchase_order.py
odoo/addons/purchase_minimum_amount/tests/__init__.py
odoo/addons/purchase_minimum_amount/tests/test_po_minimum_amount_block.py
odoo/addons/purchase_minimum_amount/views/purchase_order_view.xml
odoo/addons/purchase_minimum_amount/views/res_partner_view.xml
odoo11_addon_purchase_minimum_amount-11.0.1.0.0.dist-info/DESCRIPTION.rst
odoo11_addon_purchase_minimum_amount-11.0.1.0.0.dist-info/METADATA
odoo11_addon_purchase_minimum_amount-11.0.1.0.0.dist-info/RECORD
odoo11_addon_purchase_minimum_amount-11.0.1.0.0.dist-info/WHEEL
odoo11_addon_purchase_minimum_amount-11.0.1.0.0.dist-info/metadata.json
odoo11_addon_purchase_minimum_amount-11.0.1.0.0.dist-info/top_level.txt
